ikan/ChebyKAN.py
ikan/FourierKAN.py
ikan/GroupKAN.py
ikan/JacobiKAN.py
ikan/KAN.py
ikan/TaylorKAN.py
ikan/WaveletKAN.py
ikan/__init__.py
ikan/kat_1dgroup.py
ikan/kat_1dgroup_torch.py
ikan/kat_1dgroup_triton.py
ikan/kat_2dgroup_triton.py
ikan/rational_triton.py
ikan/rational_triton2d.py
ikan/kat_rational/__init__.py
ikan/kat_rational/fit.py
ikan/kat_rational/gain.py
ikan/kat_rational/kat_1dgroup.py
ikan/kat_rational/kat_1dgroup_torch.py
ikan/kat_rational/kat_1dgroup_triton.py
ikan/kat_rational/kat_2dgroup_triton.py
ikan/kat_rational/rational_triton.py
ikan/kat_rational/rational_triton2d.py
ikan-1.3.0.dist-info/LICENSE
ikan-1.3.0.dist-info/METADATA
ikan-1.3.0.dist-info/WHEEL
ikan-1.3.0.dist-info/top_level.txt
ikan-1.3.0.dist-info/RECORD
