Metadata-Version: 2.1
Name: ikan
Version: 1.3.0
Summary: An efficient KAN implementation in Chinese.
Home-page: https://github.com/lgy112112/Efficient-KAN-in-Chinese
Author: Guoying LIAO
Author-email: lgy112112@gmail.com
License: UNKNOWN
Platform: UNKNOWN
Classifier: Programming Language :: Python :: 3
Classifier: License :: OSI Approved :: MIT License
Classifier: Operating System :: OS Independent
Requires-Python: >=3.6
License-File: LICENSE
Requires-Dist: torch>=1.9.0
Requires-Dist: torchinfo
Requires-Dist: numpy
Requires-Dist: scikit-learn
Requires-Dist: timm
